matematicas/__init__.py
matematicas/funciones_matematicas.py
arnautaga_GTDM_Functions-0.0.1.dist-info/METADATA
arnautaga_GTDM_Functions-0.0.1.dist-info/WHEEL
arnautaga_GTDM_Functions-0.0.1.dist-info/top_level.txt
arnautaga_GTDM_Functions-0.0.1.dist-info/RECORD
