Metadata-Version: 2.1
Name: arnautaga-GTDM-Functions
Version: 0.0.1
Requires-Dist: numpy
Requires-Dist: scipy
